stac_sample_maker/__init__.py
stac_sample_maker/cli.py
stac_sample_maker/generator.py
stac_sample_maker/providers/__init__.py
stac_sample_maker/providers/eo.py
stac_sample_maker/providers/file.py
stac_sample_maker/providers/landsat.py
stac_sample_maker/providers/proj.py
stac_sample_maker/providers/sar.py
stac_sample_maker/providers/sci.py
stac_sample_maker/providers/view.py
stac_sample_maker-0.0.2.dist-info/METADATA
stac_sample_maker-0.0.2.dist-info/WHEEL
stac_sample_maker-0.0.2.dist-info/entry_points.txt
stac_sample_maker-0.0.2.dist-info/licenses/LICENSE
stac_sample_maker-0.0.2.dist-info/RECORD
