Metadata-Version: 2.4
Name: stac-sample-maker
Version: 0.0.2
Summary: Generate synthetic STAC (SpatioTemporal Asset Catalog) items with realistic metadata
Project-URL: Homepage, https://github.com/developmentseed/stac-sample-maker
Project-URL: Repository, https://github.com/developmentseed/stac-sample-maker
Project-URL: Issues, https://github.com/developmentseed/stac-sample-maker/issues
Author-email: David Bitner <bitner@dbspatial.com>
License: MIT
License-File: LICENSE
Keywords: geospatial,remote-sensing,satellite,stac,synthetic-data
Classifier: Development Status :: 4 - Beta
Classifier: Intended Audience :: Developers
Classifier: Intended Audience :: Science/Research
Classifier: License :: OSI Approved :: MIT License
Classifier: Programming Language :: Python :: 3
Classifier: Programming Language :: Python :: 3.10
Classifier: Programming Language :: Python :: 3.11
Classifier: Programming Language :: Python :: 3.12
Classifier: Topic :: Scientific/Engineering :: GIS
Classifier: Topic :: Software Development :: Libraries :: Python Modules
Classifier: Topic :: Software Development :: Testing
Requires-Python: >=3.10
Requires-Dist: faker>=19
Provides-Extra: validation
Requires-Dist: stac-validator>=3.0.0; extra == 'validation'
